{"cameraMode":{"drawMode":0,"name":"Shaded","section":"Shading Mode"},"sceneLighting":true,"audioPlay":false,"sceneViewState":{"m_AlwaysRefresh":false,"showFog":true,"showSkybox":true,"showFlares":true,"showImageEffects":true,"showParticleSystems":true,"showVisualEffectGraphs":true,"m_FxEnabled":true},"in2DMode":false,"pivot":{"x":1.4662309885025025,"y":-0.13695546984672547,"z":5.784420490264893},"rotation":{"x":-0.09064114838838577,"y":-0.10972801595926285,"z":0.00998853798955679,"w":-0.98982834815979},"size":4.252875804901123,"orthographic":false}